results_schema/__init__.py
results_schema/alembic.ini
results_schema/factories.py
results_schema/model_group_stored_procedure.sql
results_schema/schema.py
results_schema/alembic/env.py
results_schema/alembic/versions/0d44655e35fd_.py
results_schema/alembic/versions/264245ddfce2_.py
results_schema/alembic/versions/72ac5cbdca05_change_importance_to_float.py
results_schema/alembic/versions/7d57d1cf3429_.py
results_schema/alembic/versions/8b3f167d0418_.py
results_schema-2.0.0.dist-info/DESCRIPTION.rst
results_schema-2.0.0.dist-info/METADATA
results_schema-2.0.0.dist-info/RECORD
results_schema-2.0.0.dist-info/WHEEL
results_schema-2.0.0.dist-info/metadata.json
results_schema-2.0.0.dist-info/top_level.txt
