Metadata-Version: 2.0
Name: results-schema
Version: 2.0.0
Summary: Store results of modeling runs
Home-page: https://github.com/dssg/results-schema
Author: Center for Data Science and Public Policy
Author-email: datascifellows@gmail.com
License: BY DOWNLOADING results-schema PROGRAM YOU AGREE TO THE FOLLOWING TERMS OF USE:
Requires-Dist: alembic
Requires-Dist: factory-boy
Requires-Dist: psycopg2
Requires-Dist: pyyaml
Requires-Dist: sqlalchemy
